cable_car/__init__.py
cable_car/broadcast_connector.py
cable_car/byte_messages.py
cable_car/direct_connect.py
cable_car/json_messages.py
cable_car/messenger.py
cable_car-1.0.1.dist-info/LICENSE
cable_car-1.0.1.dist-info/WHEEL
cable_car-1.0.1.dist-info/METADATA
cable_car-1.0.1.dist-info/RECORD
