Metadata-Version: 2.1
Name: cable_car
Version: 1.0.1
Summary: A lightweight, simple set of classes for opening a TCP socket (to a particular
Author-email: Leon Dionne <ldionne@dridesign.sh.cn>
Classifier: License :: OSI Approved :: GNU General Public License v3 or later (GPLv3+)
Requires-Dist: pytest
Requires-Dist: psutil
Project-URL: Home, https://github.com/Zen-Master-SoSo/cable_car
